misura/__init__.py
misura/__main__.py
misura/currencies.py
misura/exceptions.py
misura/globals.py
misura/quantities.py
misura/tables.py
misura/utilities.py
misura-1.6.3.dist-info/METADATA
misura-1.6.3.dist-info/WHEEL
misura-1.6.3.dist-info/licenses/LICENSE
misura-1.6.3.dist-info/RECORD
