Metadata-Version: 2.1
Name: misura
Version: 1.6.3
Summary: Python library for easy unit handling and conversion for scientific & engineering applications.
Project-URL: Homepage, https://github.com/diantonioandrea/misura
Project-URL: Documentation, https://misura.diantonioandrea.com
Project-URL: Bug Tracker, https://github.com/diantonioandrea/misura/issues
Author-email: Andrea Di Antonio <mail@diantonioandrea.com>
License-File: LICENSE
Classifier: License :: OSI Approved :: MIT License
Classifier: Operating System :: OS Independent
Classifier: Programming Language :: Python :: 3
Requires-Python: >=3.7
Requires-Dist: colorama
Requires-Dist: requests
